{
  "id": "0000000193",
  "title": "U.S. American Poetry from the 19th Century to Today",
  "type": "SE",
  "ects_credits": null,
  "course_languages": "German",
  "lecturers": [
    "Jakubzik, Heiko"
  ],
  "start_date": "2026-04-15",
  "end_date": "2026-07-22",
  "weeks": [
    {
      "day_of_week": 3,
      "start_time": "11:15",
      "end_time": "12:45",
      "location": "Übungsraum (2220.01.114)",
      "location_link": "https://heico.uni-heidelberg.de/heiCO/ee/ui/ca2/app/desktop/#/pl/ui/$ctx/ris.einzelRaum?raumKey=22606",
      "room": "Übungsraum (2220.01.114)",
      "building": "Kettengasse 12-16, 1st floor",
      "note": null
    }
  ],
  "detail_link": "https://heico.uni-heidelberg.de/heiCO/ee/ui/ca2/app/desktop/#/slc.tm.cp/student/courses/411096",
  "exceptions": [],
  "notes": "",
  "last_updated": "2026-04-12T22:26:48Z"
}
