{
  "id": "1002000811",
  "title": "Statistics with R (MSc)",
  "type": "SE",
  "ects_credits": "4",
  "course_languages": "English (primary)",
  "lecturers": [
    "Gao, Shanqing"
  ],
  "start_date": "2026-04-15",
  "end_date": "2026-07-22",
  "weeks": [
    {
      "day_of_week": 3,
      "start_date": "2026-04-15",
      "end_date": "2026-04-15",
      "start_time": "14:15",
      "end_time": "15:45",
      "location": "ÜR E 3010 EG 022 (3010.EG.023)",
      "location_link": "https://heico.uni-heidelberg.de/heiCO/ee/ui/ca2/app/desktop/#/pl/ui/$ctx/ris.einzelRaum?raumKey=23102",
      "room": "ÜR E 3010 EG 022 (3010.EG.023)",
      "building": "Hauptstraße 47-51, Ground floor",
      "note": null
    },
    {
      "day_of_week": 3,
      "start_date": "2026-04-22",
      "end_date": "2026-07-22",
      "start_time": "14:15",
      "end_time": "15:45",
      "location": "ÜR E 3010 EG 022 (3010.EG.023)",
      "location_link": "https://heico.uni-heidelberg.de/heiCO/ee/ui/ca2/app/desktop/#/pl/ui/$ctx/ris.einzelRaum?raumKey=23102",
      "room": "ÜR E 3010 EG 022 (3010.EG.023)",
      "building": "Hauptstraße 47-51, Ground floor",
      "note": null
    }
  ],
  "detail_link": "https://heico.uni-heidelberg.de/heiCO/ee/ui/ca2/app/desktop/#/slc.tm.cp/student/courses/407254",
  "exceptions": [],
  "notes": "",
  "last_updated": "2026-04-14T18:38:55Z"
}