{
  "id": "0000376642",
  "title": "3D Geodata Sensor Practical",
  "type": "PC",
  "ects_credits": "2",
  "course_languages": "English",
  "lecturers": [
    "Albert, William",
    "Tabernig, Ronald Christian"
  ],
  "start_date": "2026-04-13",
  "end_date": "2026-04-13",
  "weeks": [
    {
      "day_of_week": 1,
      "start_time": "16:00",
      "end_time": "18:00",
      "location": "Übungsraum (6348.EG.013)",
      "location_link": "https://heico.uni-heidelberg.de/heiCO/ee/ui/ca2/app/desktop/#/pl/ui/$ctx/ris.einzelRaum?raumKey=19185",
      "room": "Übungsraum (6348.EG.013)",
      "building": "Im Neuenheimer Feld 348, Ground floor",
      "note": "Vorbesprechung"
    }
  ],
  "detail_link": "https://heico.uni-heidelberg.de/heiCO/ee/ui/ca2/app/desktop/#/slc.tm.cp/student/courses/409582",
  "room": null,
  "building": null,
  "exceptions": [],
  "notes": ""
}