{
  "id": "020000140b",
  "title": "Einführung in das türkische Privatrecht",
  "type": "L",
  "ects_credits": null,
  "course_languages": "German",
  "lecturers": [
    "Akdag Güney, Necla"
  ],
  "organisation": "Faculty of Law",
  "start_date": "2026-07-27",
  "end_date": "2026-07-31",
  "weeks": [
    {
      "day_of_week": 1,
      "start_date": "2026-07-27",
      "end_date": "2026-07-27",
      "start_time": "09:00",
      "end_time": "13:00",
      "location": "Übungsraum (2150.EG.008)",
      "location_link": "https://heico.uni-heidelberg.de/heiCO/ee/ui/ca2/app/desktop/#/pl/ui/$ctx/ris.einzelRaum?raumKey=20578",
      "room": "Übungsraum (2150.EG.008)",
      "building": "Augustinergasse 9, Ground floor",
      "note": "Augustinergasse 9, Seminarraum"
    },
    {
      "day_of_week": 2,
      "start_date": "2026-07-28",
      "end_date": "2026-07-28",
      "start_time": "09:00",
      "end_time": "13:00",
      "location": "Übungsraum (2150.EG.008)",
      "location_link": "https://heico.uni-heidelberg.de/heiCO/ee/ui/ca2/app/desktop/#/pl/ui/$ctx/ris.einzelRaum?raumKey=20578",
      "room": "Übungsraum (2150.EG.008)",
      "building": "Augustinergasse 9, Ground floor",
      "note": "Augustinergasse 9, Seminarraum"
    },
    {
      "day_of_week": 3,
      "start_date": "2026-07-29",
      "end_date": "2026-07-29",
      "start_time": "09:00",
      "end_time": "13:00",
      "location": "Übungsraum (2150.EG.008)",
      "location_link": "https://heico.uni-heidelberg.de/heiCO/ee/ui/ca2/app/desktop/#/pl/ui/$ctx/ris.einzelRaum?raumKey=20578",
      "room": "Übungsraum (2150.EG.008)",
      "building": "Augustinergasse 9, Ground floor",
      "note": "Augustinergasse 9, Seminarraum"
    },
    {
      "day_of_week": 4,
      "start_date": "2026-07-30",
      "end_date": "2026-07-30",
      "start_time": "09:00",
      "end_time": "13:00",
      "location": "Übungsraum (2150.EG.008)",
      "location_link": "https://heico.uni-heidelberg.de/heiCO/ee/ui/ca2/app/desktop/#/pl/ui/$ctx/ris.einzelRaum?raumKey=20578",
      "room": "Übungsraum (2150.EG.008)",
      "building": "Augustinergasse 9, Ground floor",
      "note": "Augustinergasse 9, Seminarraum"
    },
    {
      "day_of_week": 5,
      "start_date": "2026-07-31",
      "end_date": "2026-07-31",
      "start_time": "09:00",
      "end_time": "13:00",
      "location": "Übungsraum (2150.EG.008)",
      "location_link": "https://heico.uni-heidelberg.de/heiCO/ee/ui/ca2/app/desktop/#/pl/ui/$ctx/ris.einzelRaum?raumKey=20578",
      "room": "Übungsraum (2150.EG.008)",
      "building": "Augustinergasse 9, Ground floor",
      "note": "Augustinergasse 9, Seminarraum"
    }
  ],
  "detail_link": "https://heico.uni-heidelberg.de/heiCO/ee/ui/ca2/app/desktop/#/slc.tm.cp/student/courses/416580",
  "exceptions": [],
  "further_info": "Recommended Reading werden zu Beginn der Vorlesung bekannt gegeben. Sprechstunde vor der Vorlesung IPR Raum 37",
  "last_updated": "2026-04-21T10:05:58Z"
}