{
  "id": "9207850040",
  "title": "WFT07-IO - Erfassung von Biomarkern: Big Data",
  "type": "SE",
  "ects_credits": null,
  "course_languages": "German",
  "lecturers": [
    "Budczies, Jan",
    "Kazdal, Daniel Nebil",
    "Kirchner, Martina",
    "Kluck, Klaus Henning",
    "Menzel, Michael",
    "Neumann, Olaf",
    "Volckmar, Anna-Lena"
  ],
  "start_date": "2026-05-12",
  "end_date": "2026-05-21",
  "weeks": [
    {
      "day_of_week": 2,
      "start_time": "15:15",
      "end_time": "18:15",
      "location": "Seminarraum Allgemeine Pathologie (6224.01.004)",
      "location_link": "https://heico.uni-heidelberg.de/heiCO/ee/ui/ca2/app/desktop/#/pl/ui/$ctx/ris.einzelRaum?raumKey=28784",
      "room": "Seminarraum Allgemeine Pathologie (6224.01.004)",
      "building": "Im Neuenheimer Feld 224, 1st floor",
      "note": null
    },
    {
      "day_of_week": 4,
      "start_time": "15:15",
      "end_time": "18:15",
      "location": "Seminarraum Allgemeine Pathologie (6224.01.004)",
      "location_link": "https://heico.uni-heidelberg.de/heiCO/ee/ui/ca2/app/desktop/#/pl/ui/$ctx/ris.einzelRaum?raumKey=28784",
      "room": "Seminarraum Allgemeine Pathologie (6224.01.004)",
      "building": "Im Neuenheimer Feld 224, 1st floor",
      "note": null
    }
  ],
  "detail_link": "https://heico.uni-heidelberg.de/heiCO/ee/ui/ca2/app/desktop/#/slc.tm.cp/student/courses/418288",
  "exceptions": [],
  "notes": "",
  "last_updated": "2026-04-12T22:26:48Z"
}
