{
  "id": "020000134a",
  "title": "Latein für Juristen II",
  "type": "L",
  "ects_credits": null,
  "course_languages": "German",
  "lecturers": [
    "Nitsch, Andreas"
  ],
  "organisation": "Faculty of Law",
  "start_date": "2026-04-22",
  "end_date": "2026-07-22",
  "weeks": [
    {
      "day_of_week": 3,
      "start_date": "2026-04-22",
      "end_date": "2026-07-22",
      "start_time": "18:00",
      "end_time": "20:00",
      "location": "HS 05 (2170.01.033)",
      "location_link": "https://heico.uni-heidelberg.de/heiCO/ee/ui/ca2/app/desktop/#/pl/ui/$ctx/ris.einzelRaum?raumKey=20589",
      "room": "HS 05 (2170.01.033)",
      "building": "HS 05, Grabengasse 3-5, 1st floor",
      "note": null
    },
    {
      "day_of_week": 5,
      "start_date": "2026-06-26",
      "end_date": "2026-07-17",
      "start_time": "16:00",
      "end_time": "18:00",
      "location": "HS 05 (2170.01.033)",
      "location_link": "https://heico.uni-heidelberg.de/heiCO/ee/ui/ca2/app/desktop/#/pl/ui/$ctx/ris.einzelRaum?raumKey=20589",
      "room": "HS 05 (2170.01.033)",
      "building": "HS 05, Grabengasse 3-5, 1st floor",
      "note": null
    }
  ],
  "detail_link": "https://heico.uni-heidelberg.de/heiCO/ee/ui/ca2/app/desktop/#/slc.tm.cp/student/courses/408816",
  "exceptions": [],
  "further_info": "Recommended Reading Literaturhinweise werden in der Vorlesung gegeben. Die lateinische Sprache ist eines der tragenden Fundamente der deutschen und europäischen Rechtswissenschaft. Viele Rechtsgrundsätze und Rechtsgedanken werden auch heute noch mit lateinischen Begriffen oder Lehrsätzen bezeichnet, vor allem im Zivilrecht, aber auch im Strafrecht. Die Beschäftigung mit der lateinischen Sprache schult zudem die für Juristen unabdingbare Fähigkeit, Texte sorgfältig zu analysieren und eigene Gedanken präzise zu formulieren. Die Veranstaltung vermittelt in der Form eines Sprachkurses die Grundkenntnisse der lateinischen Sprache anhand einfacher juristischer Texte aus römischer Zeit, darunter Auszüge aus dem Lehrbuch des römischen Juristen Gaius und Fragmente aus dem Corpus Iuris Civilis des oströmischen Kaisers Justinian, dessen Werk nahezu alle modernen Rechtsordnungen maßgeblich beeinflusste.",
  "last_updated": "2026-04-21T10:26:35Z"
}