{
  "id": "0000000068",
  "title": "SE U.S. Alliance Politics in Asia",
  "type": "SE",
  "ects_credits": null,
  "course_languages": "German",
  "lecturers": [
    "Jeong, Juhee"
  ],
  "start_date": "2026-04-14",
  "end_date": "2026-07-21",
  "weeks": [
    {
      "day_of_week": 2,
      "start_time": "14:00",
      "end_time": "16:00",
      "location": "Siehe Anmerkung",
      "location_link": null,
      "room": "Siehe Anmerkung",
      "building": null,
      "note": "Ort: HCA, Stucco"
    }
  ],
  "detail_link": "https://heico.uni-heidelberg.de/heiCO/ee/ui/ca2/app/desktop/#/slc.tm.cp/student/courses/412387",
  "exceptions": [],
  "notes": "",
  "last_updated": "2026-04-12T22:26:48Z"
}
