{
  "id": "1004150006",
  "title": "(BA, M5) Praktikum im beruflichen Handlungsfeld",
  "type": "P",
  "ects_credits": "10",
  "course_languages": "German",
  "lecturers": [
    "Schultz-Coulon, Anna"
  ],
  "organisation": "Institute for Education Studies",
  "start_date": null,
  "end_date": null,
  "weeks": [],
  "detail_link": "https://heico.uni-heidelberg.de/heiCO/ee/ui/ca2/app/desktop/#/slc.tm.cp/student/courses/403831",
  "exceptions": [],
  "further_info": "15 ECTS für das gesamte Modul 5 \"Praktikum im beruflichen Handlungsfeld\" (BA 75%): 10 LP Praktikum (300 Stunden in einer Einrichtung mit Bildungsbezug) 2 LP Projektarbeit (Erstellung eines (wissenschaftlichen) Posters nach abgeschlossenem Praktikum) 3 LP PROF-Day (Modulprüfung in Form einer Posterpräsentation, benotet) Anmeldung in heiCO erforderlich!",
  "last_updated": "2026-04-21T09:55:20Z"
}