{
  "id": "0000000192",
  "title": "Ü: Fachwissenschaftliche Methodenreflexion: Luthers kleiner Katechismus von 1529",
  "type": "PC",
  "ects_credits": "2",
  "course_languages": "German",
  "lecturers": [
    "Ehmann, Johannes"
  ],
  "start_date": "2026-04-13",
  "end_date": "2026-07-20",
  "weeks": [
    {
      "day_of_week": 1,
      "start_time": "11:15",
      "end_time": "12:45",
      "location": "KiGa II (1200.EG.002C)",
      "location_link": "https://heico.uni-heidelberg.de/heiCO/ee/ui/ca2/app/desktop/#/pl/ui/$ctx/ris.einzelRaum?raumKey=7443",
      "room": "KiGa II (1200.EG.002C)",
      "building": "Kisselgasse 1, Ground floor",
      "note": null
    }
  ],
  "detail_link": "https://heico.uni-heidelberg.de/heiCO/ee/ui/ca2/app/desktop/#/slc.tm.cp/student/courses/411093",
  "exceptions": [],
  "notes": "",
  "last_updated": "2026-04-12T22:26:48Z"
}
