{
  "id": "1800000010",
  "title": "Economic and Social Statistics",
  "type": "L",
  "ects_credits": null,
  "course_languages": "German",
  "lecturers": [
    "Conrad, Christian"
  ],
  "start_date": "2026-04-14",
  "end_date": "2026-07-23",
  "weeks": [
    {
      "day_of_week": 2,
      "start_time": "16:00",
      "end_time": "18:00",
      "location": "HS 15 (2170.03.025)",
      "location_link": "https://heico.uni-heidelberg.de/heiCO/ee/ui/ca2/app/desktop/#/pl/ui/$ctx/ris.einzelRaum?raumKey=20773",
      "room": "HS 15 (2170.03.025)",
      "building": "HS 15, Grabengasse 3-5, 3rd floor",
      "note": null
    },
    {
      "day_of_week": 3,
      "start_time": "09:00",
      "end_time": "11:00",
      "location": "HS 05 (2170.01.033)",
      "location_link": "https://heico.uni-heidelberg.de/heiCO/ee/ui/ca2/app/desktop/#/pl/ui/$ctx/ris.einzelRaum?raumKey=20589",
      "room": "HS 05 (2170.01.033)",
      "building": "HS 05, Grabengasse 3-5, 1st floor",
      "note": null
    },
    {
      "day_of_week": 4,
      "start_time": "14:00",
      "end_time": "16:00",
      "location": "HS 15 (2170.03.025)",
      "location_link": "https://heico.uni-heidelberg.de/heiCO/ee/ui/ca2/app/desktop/#/pl/ui/$ctx/ris.einzelRaum?raumKey=20773",
      "room": "HS 15 (2170.03.025)",
      "building": "HS 15, Grabengasse 3-5, 3rd floor",
      "note": null
    },
    {
      "day_of_week": 1,
      "start_time": "16:00",
      "end_time": "18:00",
      "location": "Heuscheuer II (2050.02.202)",
      "location_link": "https://heico.uni-heidelberg.de/heiCO/ee/ui/ca2/app/desktop/#/pl/ui/$ctx/ris.einzelRaum?raumKey=9376",
      "room": "Heuscheuer II (2050.02.202)",
      "building": "Heuscheuer II, Große Mantelgasse 2, 2nd floor",
      "note": "Ersatztermin wg. Feiertag"
    },
    {
      "day_of_week": 4,
      "start_time": "16:00",
      "end_time": "18:00",
      "location": "HS 15 (2170.03.025)",
      "location_link": "https://heico.uni-heidelberg.de/heiCO/ee/ui/ca2/app/desktop/#/pl/ui/$ctx/ris.einzelRaum?raumKey=20773",
      "room": "HS 15 (2170.03.025)",
      "building": "HS 15, Grabengasse 3-5, 3rd floor",
      "note": null
    },
    {
      "day_of_week": 2,
      "start_time": "08:00",
      "end_time": "11:00",
      "location": "HS 13 (2170.02.018)",
      "location_link": "https://heico.uni-heidelberg.de/heiCO/ee/ui/ca2/app/desktop/#/pl/ui/$ctx/ris.einzelRaum?raumKey=20616",
      "room": "HS 13 (2170.02.018)",
      "building": "HS 13, Grabengasse 3-5, 2nd floor",
      "note": null
    }
  ],
  "detail_link": "https://heico.uni-heidelberg.de/heiCO/ee/ui/ca2/app/desktop/#/slc.tm.cp/student/courses/409152",
  "exceptions": [],
  "notes": "",
  "last_updated": "2026-04-12T22:26:48Z"
}
