{
  "id": "0072060074",
  "title": "Klaviermusik in Wien zur Zeit Beethovens und Schuberts",
  "type": "SE",
  "ects_credits": null,
  "course_languages": "German",
  "lecturers": [
    "Flamm, Christoph"
  ],
  "organisation": "Musicology Seminar",
  "start_date": "2026-04-23",
  "end_date": "2026-07-23",
  "weeks": [
    {
      "day_of_week": 4,
      "start_date": "2026-04-23",
      "end_date": "2026-07-23",
      "start_time": "11:15",
      "end_time": "12:45",
      "location": "Siehe Anmerkung",
      "location_link": null,
      "room": "Siehe Anmerkung",
      "building": null,
      "note": "Hörsaal des Musikwissenschaftlichen Seminars"
    }
  ],
  "detail_link": "https://heico.uni-heidelberg.de/heiCO/ee/ui/ca2/app/desktop/#/slc.tm.cp/student/courses/412504",
  "exceptions": [],
  "further_info": "Recommended Reading • Otto Biba, „Die Wiener Klavierszene um 1800. Klavierunterricht, Klavierspiel, Klaviermusik, Klavierbau“, in: Richard Bösel (Hrsg.), La cultura del fortepiano / Die Kultur des Hammerklaviers 1770-1830, Atti del convegno internazionali di studi / Akten der internationalen Studientagung, Roma, 26-29 Maggio 2004 / Rom, 26.-29. Mai 2004, Bologna 2009, S.231-259 • Matthew Gardner / Christine Martin (Hrsg), Schubert’s Piano, Cambridge 2024 (auch online) • Siegbert Rampe, Beethovens Klaviere und seine Klavierimprovisation. Klangwelt und Aufführungspraxis, München / Salzburg 2015",
  "last_updated": "2026-04-21T10:24:07Z"
}