{
  "id": "1005001050",
  "title": "Bewegungsinterventionen gestalten und umsetzen",
  "type": "PC",
  "ects_credits": "2",
  "course_languages": "German",
  "lecturers": [
    "Roth, Christina"
  ],
  "organisation": "Institute of Sports and Sports Sciences",
  "start_date": null,
  "end_date": null,
  "weeks": [],
  "detail_link": "https://heico.uni-heidelberg.de/heiCO/ee/ui/ca2/app/desktop/#/slc.tm.cp/student/courses/414563",
  "exceptions": [],
  "further_info": "findet im Sommersemester 2026 nicht statt",
  "last_updated": "2026-04-21T09:56:30Z"
}