{
  "id": "9207850103",
  "title": "WFT07-IO - W_Immun-Checkpoint-Moleküle (ICPs) in der Krebstherapie_09.06.2026",
  "type": "SE",
  "ects_credits": null,
  "course_languages": "German",
  "lecturers": [
    "Karakhanova, Svetlana"
  ],
  "start_date": "2026-06-09",
  "end_date": "2026-06-09",
  "weeks": [
    {
      "day_of_week": 2,
      "start_time": "15:15",
      "end_time": "16:45",
      "location": "Online",
      "location_link": null,
      "room": "Online",
      "building": null,
      "note": null
    }
  ],
  "detail_link": "https://heico.uni-heidelberg.de/heiCO/ee/ui/ca2/app/desktop/#/slc.tm.cp/student/courses/417757",
  "exceptions": [],
  "notes": "",
  "last_updated": "2026-04-12T22:26:48Z"
}
