{
  "id": "7210SM2001",
  "title": "DSCB Focus2 Lecture \"Stem Cell Biology\"",
  "type": "L",
  "ects_credits": null,
  "course_languages": "English",
  "lecturers": [
    "Bageritz, Josephine",
    "Boutros, Michael",
    "Centanin, Lazaro",
    "Lohmann, Ingrid",
    "Lohmann, Jan",
    "Maizel, Alexis",
    "Martin-Villalba, Ana",
    "Pereira, Gislene",
    "Wittbrodt, Joachim"
  ],
  "organisation": "Centre for Organismal Studies Heidelberg (COS)",
  "start_date": null,
  "end_date": null,
  "weeks": [],
  "detail_link": "https://heico.uni-heidelberg.de/heiCO/ee/ui/ca2/app/desktop/#/slc.tm.cp/student/courses/414761",
  "exceptions": [],
  "further_info": "online information e-learning course",
  "last_updated": "2026-04-21T10:05:27Z"
}