{
  "id": "1005001034",
  "title": "Sportmedizin 2 (Sportphysiologie)",
  "type": "L",
  "ects_credits": "3",
  "course_languages": "German",
  "lecturers": [
    "Friedmann-Bette, Birgit"
  ],
  "start_date": "2026-04-16",
  "end_date": "2026-07-23",
  "weeks": [
    {
      "day_of_week": 4,
      "start_time": "16:15",
      "end_time": "17:45",
      "location": "Siehe Anmerkung",
      "location_link": null,
      "room": "Siehe Anmerkung",
      "building": null,
      "note": "Hörsaal INF 410"
    }
  ],
  "detail_link": "https://heico.uni-heidelberg.de/heiCO/ee/ui/ca2/app/desktop/#/slc.tm.cp/student/courses/414605",
  "exceptions": [],
  "notes": "",
  "last_updated": "2026-04-12T22:26:48Z"
}
